sirc/__init__.py
sirc/core/__init__.py
sirc/core/device.py
sirc/core/device.pyi
sirc/core/logic.py
sirc/core/logic.pyi
sirc/core/node.py
sirc/core/node.pyi
sirc/core/transistor.py
sirc/core/transistor.pyi
sirc/simulator/__init__.py
sirc/simulator/device.py
sirc/simulator/device.pyi
sirc-1.0.0.dist-info/METADATA
sirc-1.0.0.dist-info/WHEEL
sirc-1.0.0.dist-info/top_level.txt
sirc-1.0.0.dist-info/RECORD
