Metadata-Version: 2.4
Name: sirc
Version: 1.0.0
Summary: SIRC - Digital Logic and Circuit Simulation Engine
Author-email: CRISvsGAME <cris@crisvsgame.com>
Maintainer-email: CRISvsGAME <cris@crisvsgame.com>
License-Expression: MIT
Project-URL: Repository, https://github.com/CRISvsGAME/sirc.git
Keywords: digital logic,circuit simulation,simulation engine
Classifier: Development Status :: 5 - Production/Stable
Classifier: Intended Audience :: Developers
Classifier: Operating System :: OS Independent
Classifier: Programming Language :: Python
Classifier: Topic :: Scientific/Engineering
Requires-Python: >=3.12
Provides-Extra: dev
Requires-Dist: build; extra == "dev"
Requires-Dist: mypy; extra == "dev"
Requires-Dist: pylint; extra == "dev"
Requires-Dist: pytest; extra == "dev"
Requires-Dist: twine; extra == "dev"
